jinsh/__init__.py
jinsh/config.py
jinsh/db.py
jinsh/dboper.py
jinsh/dbutil.py
jinsh/ociTool.py
jinsh/oracle_db.py
jinsh/shutil_tools.py
jinsh/test.py
jinsh/tool.py
jinsh/word.py
jinsh-0.25.dist-info/METADATA
jinsh-0.25.dist-info/WHEEL
jinsh-0.25.dist-info/top_level.txt
jinsh-0.25.dist-info/RECORD
